{
    "number": 1,
    "text": "Hello! You've reached Serenity Beauty Salon, where we bring your beauty vision to life.",
    "is_target": false,
    "children": [
        {
            "number": 1,
            "text": "To book an appointment, press 1.",
            "is_target": false,
            "children": [
                {
                    "number": 1,
                    "text": "For appointment inquiries, press 1.",
                    "is_target": false,
                    "children": [
                        {
                            "number": 1,
                            "text": "For new appointment bookings, press 1.",
                            "is_target": false,
                            "children": []
                        },
                        {
                            "number": 2,
                            "text": "To modify an existing appointment, press 2.",
                            "is_target": false,
                            "children": []
                        },
                        {
                            "number": 3,
                            "text": "To cancel an appointment, press 3.",
                            "is_target": false,
                            "children": []
                        }
                    ]
                },
                {
                    "number": 2,
                    "text": "For service details, press 2.",
                    "is_target": false,
                    "children": [
                        {
                            "number": 1,
                            "text": "For booking inquiries, press 1 to speak with a live customer service agent.",
                            "is_target": true,
                            "children": []
                        },
                        {
                            "number": 2,
                            "text": "For information on our services, press 2 for a detailed automated response.",
                            "is_target": false,
                            "children": []
                        },
                        {
                            "number": 3,
                            "text": "To check appointment availability, press 3 for a menu of options.",
                            "is_target": false,
                            "children": []
                        }
                    ]
                },
                {
                    "number": 3,
                    "text": "To hear our pricing options, press 3.",
                    "is_target": false,
                    "children": [
                        {
                            "number": 1,
                            "text": "For immediate assistance with your appointment, press 1 to speak with a customer service agent.",
                            "is_target": true,
                            "children": []
                        },
                        {
                            "number": 2,
                            "text": "To hear our pricing options for different services, press 2.",
                            "is_target": false,
                            "children": []
                        },
                        {
                            "number": 3,
                            "text": "For frequently asked questions, press 3 to hear automated responses.",
                            "is_target": false,
                            "children": []
                        }
                    ]
                }
            ]
        },
        {
            "number": 2,
            "text": "For information on services, press 2.",
            "is_target": false,
            "children": [
                {
                    "number": 1,
                    "text": "For information on hair services, press 1.",
                    "is_target": false,
                    "children": [
                        {
                            "number": 1,
                            "text": "For pricing information on hair services, press 1.",
                            "is_target": false,
                            "children": []
                        },
                        {
                            "number": 2,
                            "text": "To hear about our hair care products, press 2.",
                            "is_target": false,
                            "children": []
                        },
                        {
                            "number": 3,
                            "text": "For tips on hair styling, press 3.",
                            "is_target": false,
                            "children": []
                        }
                    ]
                },
                {
                    "number": 2,
                    "text": "For information on skincare services, press 2.",
                    "is_target": false,
                    "children": [
                        {
                            "number": 1,
                            "text": "For questions about our skincare products, press 1.",
                            "is_target": false,
                            "children": []
                        },
                        {
                            "number": 2,
                            "text": "To schedule a skincare consultation, press 2.",
                            "is_target": false,
                            "children": []
                        },
                        {
                            "number": 3,
                            "text": "To speak with a skincare expert, press 3.",
                            "is_target": true,
                            "children": []
                        }
                    ]
                },
                {
                    "number": 3,
                    "text": "For information on nail services, press 3.",
                    "is_target": false,
                    "children": [
                        {
                            "number": 1,
                            "text": "To speak with a customer service agent for further assistance, press 1.",
                            "is_target": true,
                            "children": []
                        },
                        {
                            "number": 2,
                            "text": "For a list of our nail services and pricing, press 2.",
                            "is_target": false,
                            "children": []
                        },
                        {
                            "number": 3,
                            "text": "To hear our frequently asked questions about nail services, press 3.",
                            "is_target": false,
                            "children": []
                        }
                    ]
                }
            ]
        },
        {
            "number": 3,
            "text": "To check our operating hours, press 3.",
            "is_target": false,
            "children": [
                {
                    "number": 1,
                    "text": "For immediate assistance with your appointment, press 1 to speak with a live customer service agent.",
                    "is_target": true,
                    "children": []
                },
                {
                    "number": 2,
                    "text": "To hear our operating hours and services, press 2.",
                    "is_target": false,
                    "children": [
                        {
                            "number": 1,
                            "text": "To speak directly with a customer service agent, press 1.",
                            "is_target": true,
                            "children": []
                        },
                        {
                            "number": 2,
                            "text": "To hear our automated response regarding our services, press 2.",
                            "is_target": false,
                            "children": []
                        },
                        {
                            "number": 3,
                            "text": "For information about our promotions, press 3.",
                            "is_target": false,
                            "children": []
                        }
                    ]
                },
                {
                    "number": 3,
                    "text": "For information about our beauty products, press 3.",
                    "is_target": false,
                    "children": [
                        {
                            "number": 1,
                            "text": "For information about our hair care services, press 1.",
                            "is_target": false,
                            "children": []
                        },
                        {
                            "number": 2,
                            "text": "To learn more about our skincare treatments, press 2.",
                            "is_target": false,
                            "children": []
                        },
                        {
                            "number": 3,
                            "text": "For details on our makeup consultations, press 3.",
                            "is_target": false,
                            "children": []
                        }
                    ]
                }
            ]
        }
    ]
}