{
    "number": 1,
    "text": "Welcome to Tech Haven Electronics, where innovation meets convenience!",
    "is_target": false,
    "children": [
        {
            "number": 1,
            "text": "For product support, press 1.",
            "is_target": false,
            "children": [
                {
                    "number": 1,
                    "text": "For troubleshooting assistance, press 1.",
                    "is_target": false,
                    "children": [
                        {
                            "number": 1,
                            "text": "For general troubleshooting tips, press 1.",
                            "is_target": false,
                            "children": []
                        },
                        {
                            "number": 2,
                            "text": "For software updates and downloads, press 2.",
                            "is_target": false,
                            "children": []
                        },
                        {
                            "number": 3,
                            "text": "For device setup instructions, press 3.",
                            "is_target": false,
                            "children": []
                        }
                    ]
                },
                {
                    "number": 2,
                    "text": "For warranty information, press 2.",
                    "is_target": false,
                    "children": [
                        {
                            "number": 1,
                            "text": "For troubleshooting assistance, press 1.",
                            "is_target": false,
                            "children": []
                        },
                        {
                            "number": 2,
                            "text": "For user manuals and guides, press 2.",
                            "is_target": false,
                            "children": []
                        },
                        {
                            "number": 3,
                            "text": "For FAQs about our products, press 3.",
                            "is_target": false,
                            "children": []
                        }
                    ]
                },
                {
                    "number": 3,
                    "text": "For software updates, press 3.",
                    "is_target": false,
                    "children": [
                        {
                            "number": 1,
                            "text": "To speak with a customer service representative, press 1.",
                            "is_target": true,
                            "children": []
                        },
                        {
                            "number": 2,
                            "text": "For troubleshooting tips and guides, press 2.",
                            "is_target": false,
                            "children": []
                        },
                        {
                            "number": 3,
                            "text": "To check the status of your warranty, press 3.",
                            "is_target": false,
                            "children": []
                        }
                    ]
                }
            ]
        },
        {
            "number": 2,
            "text": "For order tracking, press 2.",
            "is_target": false,
            "children": [
                {
                    "number": 1,
                    "text": "For tracking your order status, press 1.",
                    "is_target": false,
                    "children": [
                        {
                            "number": 1,
                            "text": "To check the status of your order, press 1.",
                            "is_target": false,
                            "children": []
                        },
                        {
                            "number": 2,
                            "text": "To change your delivery address, press 2.",
                            "is_target": false,
                            "children": []
                        },
                        {
                            "number": 3,
                            "text": "For information on delivery options, press 3.",
                            "is_target": false,
                            "children": []
                        }
                    ]
                },
                {
                    "number": 2,
                    "text": "To modify your order, press 2.",
                    "is_target": false,
                    "children": [
                        {
                            "number": 1,
                            "text": "For checking order status, press 1.",
                            "is_target": false,
                            "children": []
                        },
                        {
                            "number": 2,
                            "text": "For making changes to your shipping address, press 2.",
                            "is_target": false,
                            "children": []
                        },
                        {
                            "number": 3,
                            "text": "For inquiring about delivery times, press 3.",
                            "is_target": false,
                            "children": []
                        }
                    ]
                },
                {
                    "number": 3,
                    "text": "For shipping information, press 3.",
                    "is_target": false,
                    "children": [
                        {
                            "number": 1,
                            "text": "To speak with a customer service representative, press 1.",
                            "is_target": true,
                            "children": []
                        },
                        {
                            "number": 2,
                            "text": "For information on our return policy, press 2.",
                            "is_target": false,
                            "children": []
                        },
                        {
                            "number": 3,
                            "text": "To check the status of your warranty, press 3.",
                            "is_target": false,
                            "children": []
                        },
                        {
                            "number": 4,
                            "text": "For FAQs, press 4.",
                            "is_target": false,
                            "children": []
                        }
                    ]
                },
                {
                    "number": 0,
                    "text": "",
                    "is_target": false,
                    "children": [
                        {
                            "number": 1,
                            "text": "For tracking your order status, press 1.",
                            "is_target": false,
                            "children": []
                        },
                        {
                            "number": 2,
                            "text": "To change your shipping address, press 2.",
                            "is_target": false,
                            "children": []
                        },
                        {
                            "number": 3,
                            "text": "For delivery issues, press 3.",
                            "is_target": false,
                            "children": []
                        }
                    ]
                }
            ]
        },
        {
            "number": 3,
            "text": "For warranty information, press 3.",
            "is_target": false,
            "children": [
                {
                    "number": 1,
                    "text": "For warranty claims, press 1.",
                    "is_target": false,
                    "children": [
                        {
                            "number": 1,
                            "text": "For information on warranty terms, press 1.",
                            "is_target": false,
                            "children": []
                        },
                        {
                            "number": 2,
                            "text": "To check the status of your warranty claim, press 2.",
                            "is_target": false,
                            "children": []
                        },
                        {
                            "number": 3,
                            "text": "For assistance with warranty registration, press 3.",
                            "is_target": false,
                            "children": []
                        }
                    ]
                },
                {
                    "number": 2,
                    "text": "For product registration, press 2.",
                    "is_target": false,
                    "children": [
                        {
                            "number": 1,
                            "text": "For warranty coverage details, press 1.",
                            "is_target": false,
                            "children": []
                        },
                        {
                            "number": 2,
                            "text": "To check the status of your warranty claim, press 2.",
                            "is_target": false,
                            "children": []
                        },
                        {
                            "number": 3,
                            "text": "For warranty FAQs, press 3.",
                            "is_target": false,
                            "children": []
                        }
                    ]
                },
                {
                    "number": 3,
                    "text": "For warranty policy details, press 3.",
                    "is_target": false,
                    "children": [
                        {
                            "number": 1,
                            "text": "To speak with a customer service agent about your warranty, press 1.",
                            "is_target": true,
                            "children": []
                        },
                        {
                            "number": 2,
                            "text": "For information on warranty claims, press 2.",
                            "is_target": false,
                            "children": []
                        },
                        {
                            "number": 3,
                            "text": "To check the status of your warranty request, press 3.",
                            "is_target": false,
                            "children": []
                        }
                    ]
                }
            ]
        }
    ]
}