{
    "number": 1,
    "text": "Hello! You've dialed into Auto Emporium, where your dream car awaits!",
    "is_target": false,
    "children": [
        {
            "number": 1,
            "text": "For vehicle financing options, press 1.",
            "is_target": false,
            "children": [
                {
                    "number": 1,
                    "text": "For information on loan rates, press 1.",
                    "is_target": false,
                    "children": [
                        {
                            "number": 1,
                            "text": "For assistance with your loan application, press 1 to speak with a customer service representative.",
                            "is_target": true,
                            "children": []
                        },
                        {
                            "number": 2,
                            "text": "For information on loan terms and conditions, press 2 to hear automated details.",
                            "is_target": false,
                            "children": []
                        },
                        {
                            "number": 3,
                            "text": "To check the status of your loan, press 3 for an automated update.",
                            "is_target": false,
                            "children": []
                        }
                    ]
                },
                {
                    "number": 2,
                    "text": "To apply for financing online, press 2.",
                    "is_target": false,
                    "children": [
                        {
                            "number": 1,
                            "text": "For information on financing rates, press 1.",
                            "is_target": false,
                            "children": []
                        },
                        {
                            "number": 2,
                            "text": "To check your financing application status, press 2.",
                            "is_target": false,
                            "children": []
                        },
                        {
                            "number": 3,
                            "text": "For frequently asked questions about financing, press 3.",
                            "is_target": false,
                            "children": []
                        }
                    ]
                },
                {
                    "number": 3,
                    "text": "For assistance with an existing application, press 3.",
                    "is_target": false,
                    "children": [
                        {
                            "number": 1,
                            "text": "For information on financing rates, press 1.",
                            "is_target": false,
                            "children": []
                        },
                        {
                            "number": 2,
                            "text": "To check the status of your application, press 2.",
                            "is_target": false,
                            "children": []
                        },
                        {
                            "number": 3,
                            "text": "For FAQs regarding financing, press 3.",
                            "is_target": false,
                            "children": []
                        }
                    ]
                }
            ]
        },
        {
            "number": 2,
            "text": "To check on the status of your current application, press 2.",
            "is_target": false,
            "children": [
                {
                    "number": 1,
                    "text": "To update your application information, press 1.",
                    "is_target": false,
                    "children": [
                        {
                            "number": 1,
                            "text": "For updates on your application status, press 1.",
                            "is_target": false,
                            "children": []
                        },
                        {
                            "number": 2,
                            "text": "To modify your application details, press 2.",
                            "is_target": false,
                            "children": []
                        },
                        {
                            "number": 3,
                            "text": "For assistance with application documents, press 3.",
                            "is_target": false,
                            "children": []
                        }
                    ]
                },
                {
                    "number": 2,
                    "text": "To inquire about loan options, press 2.",
                    "is_target": false,
                    "children": [
                        {
                            "number": 1,
                            "text": "For immediate assistance with your application status, press 1 to speak with a customer service representative.",
                            "is_target": true,
                            "children": []
                        },
                        {
                            "number": 2,
                            "text": "To check our FAQ regarding loan options, press 2 for automated information.",
                            "is_target": false,
                            "children": []
                        },
                        {
                            "number": 3,
                            "text": "For updates on loan application processing times, press 3 to hear recorded updates.",
                            "is_target": false,
                            "children": []
                        },
                        {
                            "number": 1,
                            "text": "For immediate assistance with your application status, press 1 to speak with a customer service representative.",
                            "is_target": true,
                            "children": []
                        },
                        {
                            "number": 2,
                            "text": "To check our FAQ regarding loan options, press 2 for automated information.",
                            "is_target": false,
                            "children": []
                        },
                        {
                            "number": 3,
                            "text": "For updates on loan application processing times, press 3 to hear recorded updates.",
                            "is_target": false,
                            "children": []
                        },
                        {
                            "number": 1,
                            "text": "For immediate assistance with your application status, press 1 to speak with a customer service representative.",
                            "is_target": true,
                            "children": []
                        },
                        {
                            "number": 2,
                            "text": "To check our FAQ regarding loan options, press 2 for automated information.",
                            "is_target": false,
                            "children": []
                        },
                        {
                            "number": 3,
                            "text": "For updates on loan application processing times, press 3 to hear recorded updates.",
                            "is_target": false,
                            "children": []
                        }
                    ]
                },
                {
                    "number": 3,
                    "text": "To check the status of your vehicle order, press 3.",
                    "is_target": false,
                    "children": [
                        {
                            "number": 1,
                            "text": "To check the status of your application, press 1.",
                            "is_target": false,
                            "children": []
                        },
                        {
                            "number": 2,
                            "text": "To get information about application requirements, press 2.",
                            "is_target": false,
                            "children": []
                        },
                        {
                            "number": 3,
                            "text": "To speak with an application specialist, press 3.",
                            "is_target": false,
                            "children": []
                        }
                    ]
                }
            ]
        },
        {
            "number": 3,
            "text": "For information on vehicle maintenance and service, press 3.",
            "is_target": false,
            "children": [
                {
                    "number": 1,
                    "text": "For service appointment scheduling, press 1.",
                    "is_target": false,
                    "children": [
                        {
                            "number": 1,
                            "text": "To hear our service hours and policies, press 1.",
                            "is_target": false,
                            "children": []
                        },
                        {
                            "number": 2,
                            "text": "To check the status of your service appointment, press 2.",
                            "is_target": false,
                            "children": []
                        },
                        {
                            "number": 3,
                            "text": "For information on our vehicle maintenance packages, press 3.",
                            "is_target": false,
                            "children": []
                        }
                    ]
                },
                {
                    "number": 2,
                    "text": "For maintenance tips and advice, press 2.",
                    "is_target": false,
                    "children": [
                        {
                            "number": 1,
                            "text": "For routine maintenance schedules, press 1.",
                            "is_target": false,
                            "children": []
                        },
                        {
                            "number": 2,
                            "text": "For service appointment inquiries, press 2.",
                            "is_target": false,
                            "children": []
                        },
                        {
                            "number": 3,
                            "text": "For troubleshooting common issues, press 3.",
                            "is_target": false,
                            "children": []
                        }
                    ]
                },
                {
                    "number": 3,
                    "text": "To speak directly with a customer service agent, press 3.",
                    "is_target": true,
                    "children": []
                }
            ]
        }
    ]
}