{
    "number": 1,
    "text": "Thank you for calling Page Turners Bookstore, where every story begins with you!",
    "is_target": false,
    "children": [
        {
            "number": 1,
            "text": "For book availability, press 1.",
            "is_target": false,
            "children": [
                {
                    "number": 1,
                    "text": "To check the availability of a specific book, press 1.",
                    "is_target": false,
                    "children": [
                        {
                            "number": 1,
                            "text": "To speak with a customer service representative about a specific book, press 1.",
                            "is_target": true,
                            "children": []
                        },
                        {
                            "number": 2,
                            "text": "For information on upcoming book releases and events, press 2.",
                            "is_target": false,
                            "children": []
                        },
                        {
                            "number": 3,
                            "text": "To hear about our return policy and procedures, press 3.",
                            "is_target": false,
                            "children": []
                        }
                    ]
                },
                {
                    "number": 2,
                    "text": "To find out about new arrivals and bestsellers, press 2.",
                    "is_target": false,
                    "children": [
                        {
                            "number": 1,
                            "text": "For checking book availability, press 1.",
                            "is_target": false,
                            "children": []
                        },
                        {
                            "number": 2,
                            "text": "For inquiries about new arrivals, press 2.",
                            "is_target": false,
                            "children": []
                        },
                        {
                            "number": 3,
                            "text": "For information on bestsellers, press 3.",
                            "is_target": false,
                            "children": []
                        }
                    ]
                },
                {
                    "number": 3,
                    "text": "For information on upcoming author events, press 3.",
                    "is_target": false,
                    "children": [
                        {
                            "number": 1,
                            "text": "For checking book availability, press 1.",
                            "is_target": false,
                            "children": []
                        },
                        {
                            "number": 2,
                            "text": "For information on our loyalty program, press 2.",
                            "is_target": false,
                            "children": []
                        },
                        {
                            "number": 3,
                            "text": "For assistance with online orders, press 3.",
                            "is_target": false,
                            "children": []
                        }
                    ]
                }
            ]
        },
        {
            "number": 2,
            "text": "To check order status, press 2.",
            "is_target": false,
            "children": [
                {
                    "number": 1,
                    "text": "To track your shipment, press 1.",
                    "is_target": false,
                    "children": [
                        {
                            "number": 1,
                            "text": "For information about your order history, press 1.",
                            "is_target": false,
                            "children": []
                        },
                        {
                            "number": 2,
                            "text": "To update your shipping address, press 2.",
                            "is_target": false,
                            "children": []
                        },
                        {
                            "number": 3,
                            "text": "For assistance with returns, press 3.",
                            "is_target": false,
                            "children": []
                        }
                    ]
                },
                {
                    "number": 2,
                    "text": "To view your order history, press 2.",
                    "is_target": false,
                    "children": [
                        {
                            "number": 1,
                            "text": "To view your current orders, press 1.",
                            "is_target": false,
                            "children": []
                        },
                        {
                            "number": 2,
                            "text": "To receive tracking information, press 2.",
                            "is_target": false,
                            "children": []
                        },
                        {
                            "number": 3,
                            "text": "For assistance with returns, press 3.",
                            "is_target": false,
                            "children": []
                        }
                    ]
                },
                {
                    "number": 3,
                    "text": "For assistance with returns, press 3.",
                    "is_target": false,
                    "children": [
                        {
                            "number": 1,
                            "text": "To track your shipment, press 1.",
                            "is_target": false,
                            "children": []
                        },
                        {
                            "number": 2,
                            "text": "To check your order history, press 2.",
                            "is_target": false,
                            "children": []
                        },
                        {
                            "number": 3,
                            "text": "For information on return policies, press 3.",
                            "is_target": false,
                            "children": []
                        }
                    ]
                }
            ]
        },
        {
            "number": 3,
            "text": "For store hours and location, press 3.",
            "is_target": false,
            "children": [
                {
                    "number": 1,
                    "text": "For inquiries about store hours, press 1.",
                    "is_target": false,
                    "children": [
                        {
                            "number": 1,
                            "text": "For current store hours, press 1.",
                            "is_target": false,
                            "children": []
                        },
                        {
                            "number": 2,
                            "text": "To find the nearest Page Turners location, press 2.",
                            "is_target": false,
                            "children": []
                        },
                        {
                            "number": 3,
                            "text": "To hear our holiday hours, press 3.",
                            "is_target": false,
                            "children": []
                        }
                    ]
                },
                {
                    "number": 2,
                    "text": "To find the location of our nearest store, press 2.",
                    "is_target": false,
                    "children": [
                        {
                            "number": 1,
                            "text": "To hear our store hours, press 1.",
                            "is_target": false,
                            "children": []
                        },
                        {
                            "number": 2,
                            "text": "To find directions to our store, press 2.",
                            "is_target": false,
                            "children": []
                        },
                        {
                            "number": 3,
                            "text": "For information on upcoming events, press 3.",
                            "is_target": false,
                            "children": []
                        }
                    ]
                },
                {
                    "number": 3,
                    "text": "To speak with a customer service representative, press 3.",
                    "is_target": true,
                    "children": []
                }
            ]
        }
    ]
}